qlayers/__init__.py
qlayers/quant_layers.py
qlayers/regression.py
qlayers/thickness.py
qlayers/utils.py
qlayers/tests/__init__.py
qlayers/tests/test_quant_layers.py
qlayers/tests/test_regression.py
qlayers/tests/test_thickness.py
qlayers/tests/test_utils.py
qlayers-1.0.0.dist-info/LICENSE.md
qlayers-1.0.0.dist-info/METADATA
qlayers-1.0.0.dist-info/WHEEL
qlayers-1.0.0.dist-info/top_level.txt
qlayers-1.0.0.dist-info/RECORD
