Metadata-Version: 2.1
Name: qlayers
Version: 1.0.0
Summary: Quantitative layer analysis for renal MRI
Home-page: https://github.com/alexdaniel654/qlayers
License: GPL-3.0
Classifier: Development Status :: 4 - Beta
Classifier: Intended Audience :: Developers
Classifier: Intended Audience :: Science/Research
Classifier: Topic :: Scientific/Engineering
Classifier: Environment :: Console
Classifier: Operating System :: OS Independent
Classifier: Programming Language :: Python :: 3.9
Classifier: Programming Language :: Python :: 3.10
Classifier: Programming Language :: Python :: 3.11
Classifier: Programming Language :: Python :: 3.12
Classifier: License :: OSI Approved :: GNU General Public License v3 (GPLv3)
Requires-Python: >=3.9, <4
License-File: LICENSE.md
Requires-Dist: nibabel
Requires-Dist: numpy
Requires-Dist: pandas
Requires-Dist: pytest
Requires-Dist: rtree
Requires-Dist: scikit-image
Requires-Dist: tqdm
Requires-Dist: trimesh
